Metadata-Version: 2.1
Name: switchem
Version: 1.0.0
Summary: UNKNOWN
Home-page: UNKNOWN
Author: Perzan
Author-email: PerzanDevelopment@gmail.com
License: UNKNOWN
Platform: UNKNOWN
Requires-Python: ~=3.9
